argschema/__init__.py
argschema/argschema_parser.py
argschema/autodoc.py
argschema/deprecated.py
argschema/schemas.py
argschema/utils.py
argschema/validate.py
argschema/fields/__init__.py
argschema/fields/deprecated.py
argschema/fields/files.py
argschema/fields/loglevel.py
argschema/fields/numpyarrays.py
argschema/fields/slice.py
argschema-1.17.5.dist-info/LICENSE.txt
argschema-1.17.5.dist-info/METADATA
argschema-1.17.5.dist-info/WHEEL
argschema-1.17.5.dist-info/top_level.txt
argschema-1.17.5.dist-info/RECORD
