Metadata-Version: 2.1
Name: argschema
Version: 1.17.5
Summary: a wrapper for setting up modules that can have parameters specified by command line arguments,       json_files, or dictionary objects. Providing a common wrapper for data processing modules.
Home-page: https://github.com/AllenInstitute/argschema
Author: Forrest Collman,David Feng
Author-email: forrestc@alleninstitute.org
License: UNKNOWN
Platform: UNKNOWN
Requires-Dist: numpy
Requires-Dist: marshmallow
